fastfetchbot_telegram_bot/__init__.py
fastfetchbot_telegram_bot/bot/__init__.py
fastfetchbot_telegram_bot/bot/formatting.py
fastfetchbot_telegram_bot/bot/handlers.py
fastfetchbot_telegram_bot/bot/message_process.py
fastfetchbot_telegram_bot/config.py
fastfetchbot_telegram_bot/models/__init__.py
fastfetchbot_telegram_bot/models/files.py
fastfetchbot_telegram_bot/templates/social_media_message.jinja2
fastfetchbot_telegram_bot/utils/__init__.py
fastfetchbot_telegram_bot/utils/image.py
fastfetchbot_telegram_bot/utils/logger.py
fastfetchbot_telegram_bot/utils/network.py
fastfetchbot_telegram_bot/utils/parser.py
fastfetchbot_telegram_bot/utils/urlparser.py
fastfetchbot_telegram_bot-0.1.1.dist-info/LICENSE
fastfetchbot_telegram_bot-0.1.1.dist-info/METADATA
fastfetchbot_telegram_bot-0.1.1.dist-info/WHEEL
fastfetchbot_telegram_bot-0.1.1.dist-info/RECORD
